rtcclient/__init__.py
rtcclient/base.py
rtcclient/client.py
rtcclient/exception.py
rtcclient/models.py
rtcclient/project_area.py
rtcclient/query.py
rtcclient/template.py
rtcclient/templates/issue_example.template
rtcclient/utils.py
rtcclient/workitem.py
rtcclient-0.10.0.dist-info/LICENSE
rtcclient-0.10.0.dist-info/METADATA
rtcclient-0.10.0.dist-info/WHEEL
rtcclient-0.10.0.dist-info/RECORD
