Metadata-Version: 2.3
Name: rtcclient
Version: 0.10.0
Summary: RTCClient for Rational Team Concert
License: Apache License Version 2.0
Keywords: rtcclient,Rational Team Concert,RTC
Author: Di Xu
Author-email: stephenhsu90@gmail.com
Requires-Python: >=3.7.0,<4.0
Classifier: Development Status :: 5 - Production/Stable
Classifier: Environment :: Console
Classifier: Intended Audience :: Developers
Classifier: Intended Audience :: Information Technology
Classifier: Intended Audience :: System Administrators
Classifier: License :: OSI Approved :: Apache Software License
Classifier: License :: Other/Proprietary License
Classifier: Operating System :: OS Independent
Classifier: Programming Language :: Python
Classifier: Programming Language :: Python :: 3
Classifier: Programming Language :: Python :: 3.7
Classifier: Programming Language :: Python :: 3.8
Classifier: Programming Language :: Python :: 3.9
Classifier: Programming Language :: Python :: 3.10
Classifier: Programming Language :: Python :: 3.11
Classifier: Programming Language :: Python :: 3.12
Classifier: Programming Language :: Python :: 3.13
Classifier: Programming Language :: Python :: 3.6
Classifier: Topic :: Utilities
Requires-Dist: PySocks (>=1.5.6)
Requires-Dist: jinja2 (>=2.2)
Requires-Dist: lxml (>=5.0.0,<6.0.0)
Requires-Dist: requests (>=2.10.0)
Requires-Dist: six
Requires-Dist: xmltodict (>=0.13.0,<0.14.0)
Project-URL: Homepage, https://github.com/dixudx/rtcclient
